<?xml version="1.0" encoding="UTF-8"?>
<Simulation SimulationType="Life">
    <author>Keegan</author>
	<simulation>Life</simulation>
	<state>1</state>
    <rows>10</rows>
    <columns>10</columns>
    <values>99</values>
    <neighbors>0,1,2,3,4,5,6,7</neighbors>
    <state>1</state>
    <locations>0,0,0,1,1,1,1,1,1,1,1,1,1,0,0,0,0,1,1,1,1,1,1,1,1,1,1,1,1,1,1,1,1,1,1,0,0,1,1,1,1,1,1,1,1,1,0,0,0,1,1,1,1,1,1,1,1,1,0,0,0,0,1,1,1,1,1,1,1,1,1,1,1,1,1,1,1,1,1,1,1,1,1,1,1,1,0,0,0,0,1,1,1,1,1,1,1,1,1,1</locations>
</Simulation>
   